<Builders DateGenerated="2022-04-08T23:36:52"><Corporation><CorporateBuilderNumber>51279</CorporateBuilderNumber><CorporateState>OH</CorporateState><CorporateName>Huddleston Homes</CorporateName><Builder><BuilderNumber>51328</BuilderNumber><BrandName>Huddleston Homes</BrandName><BrandLogo_Med ReferenceType="URL">http://mlhuddleston.com/images/Logo1.jpg</BrandLogo_Med><ReportingName>Huddleston Homes</ReportingName><DefaultLeadsEmail LeadsPerMessage="All">leads@thebdx.com</DefaultLeadsEmail><BuilderWebsite>http://mlhuddleston.com/</BuilderWebsite><Subdivision Status="Active"><SubdivisionNumber>517945301278592382785997004082</SubdivisionNumber><SubdivisionName>Scarborough</SubdivisionName><BuildOnYourLot>0</BuildOnYourLot><SalesOffice><Address OutOfCommunity="0"><City>Beavercreek</City><State>OH</State><ZIP>45434</ZIP></Address></SalesOffice><SubDescription>Huddleston Homes is a residential construction company that has the desire to build its customers dream homes. With over 50 years of experience in the building industry, Huddleston Homes knows what home buyers expect. Beavercreek is popular for military personnel as the city is nearby Wright-Patterson Air Force Base.&#160;&#160;&#160;&#160;</SubDescription><SubImage SequencePosition="1" Title="House1" ReferenceType="URL">http://mlhuddleston.com/images/Banner/b1.jpg</SubImage><SubWebsite>http://mlhuddleston.com/scarborough.html</SubWebsite></Subdivision><Subdivision Status="Active"><SubdivisionNumber>614386801307835540579631238190</SubdivisionNumber><SubdivisionName>Bexley Hills</SubdivisionName><BuildOnYourLot>0</BuildOnYourLot><SalesOffice><Address OutOfCommunity="0"><City>Beavercreek</City><State>OH</State><ZIP>45434</ZIP></Address></SalesOffice><SubDescription>Huddleston Homes is a residential construction company that has the desire to build its customers dream homes. With over 50 years of experience in the building industry, Huddleston Homes knows what home buyers expect. Beavercreek is popular for military personnel as the city is nearby Wright-Patterson Air Force Base.&#160;&#160;&#160;&#160;</SubDescription><SubImage SequencePosition="1" Title="House1" ReferenceType="URL">http://mlhuddleston.com/images/Banner/b1.jpg</SubImage><SubWebsite>http://mlhuddleston.com/bexleyhills.html</SubWebsite></Subdivision><Subdivision Status="Active"><SubdivisionNumber>726787144323011499402095925281</SubdivisionNumber><SubdivisionName>Tara Falls</SubdivisionName><BuildOnYourLot>0</BuildOnYourLot><SalesOffice><Address OutOfCommunity="0"><City>Beavercreek</City><State>OH</State><ZIP>45434</ZIP></Address></SalesOffice><SubDescription>Huddleston Homes is a residential construction company that has the desire to build its customers dream homes. With over 50 years of experience in the building industry, Huddleston Homes knows what home buyers expect. Beavercreek is popular for military personnel as the city is nearby Wright-Patterson Air Force Base.&#160;&#160;&#160;&#160;</SubDescription><SubImage SequencePosition="1" Title="House1" ReferenceType="URL">http://mlhuddleston.com/images/Banner/b1.jpg</SubImage><SubWebsite>http://mlhuddleston.com/tarafalls.html</SubWebsite></Subdivision><Subdivision Status="Active"><SubdivisionNumber>971857237191755729361987799487</SubdivisionNumber><SubdivisionName>Hunters Ridge</SubdivisionName><BuildOnYourLot>0</BuildOnYourLot><SalesOffice><Address OutOfCommunity="0"><City>Beavercreek</City><State>OH</State><ZIP>45434</ZIP></Address></SalesOffice><SubDescription>Huddleston Homes is a residential construction company that has the desire to build its customers dream homes. With over 50 years of experience in the building industry, Huddleston Homes knows what home buyers expect. Beavercreek is popular for military personnel as the city is nearby Wright-Patterson Air Force Base.&#160;&#160;&#160;&#160;</SubDescription><SubImage SequencePosition="1" Title="House1" ReferenceType="URL">http://mlhuddleston.com/images/Banner/b1.jpg</SubImage><SubWebsite>http://mlhuddleston.com/huntersridge.html</SubWebsite></Subdivision></Builder></Corporation></Builders>