<Builders DateGenerated="2022-04-24T00:27:36"><Corporation><CorporateBuilderNumber>49003</CorporateBuilderNumber><CorporateState>KS</CorporateState><CorporateName>Chris George Custom Homes</CorporateName><Builder><BuilderNumber>49270</BuilderNumber><BrandName>Chris George Homes</BrandName><BrandLogo_Med ReferenceType="URL">http://www.chrisgeorgenewhomes.com/images/chris-george-logo.png</BrandLogo_Med><ReportingName>Chris George Homes</ReportingName><DefaultLeadsEmail LeadsPerMessage="All">leads@thebdx.com</DefaultLeadsEmail><BuilderWebsite>http://www.chrisgeorgenewhomes.com/</BuilderWebsite><Subdivision Status="Active"><SubdivisionNumber>49270</SubdivisionNumber><SubdivisionName>Chris George Homes</SubdivisionName><BuildOnYourLot>0</BuildOnYourLot><SalesOffice><Address OutOfCommunity="0"><Street1>128 Boston Post Road</Street1><City>Lyme</City><State>CT</State><ZIP>06333</ZIP></Address></SalesOffice><SubDescription>We believe that beautiful homes begin with customers who want to love the home in which they live &#8230; customers who don&#8217;t want to settle for a pre-owned house that doesn&#8217;t fit their needs or taste. Our philosophy for well over 30 years has been to build a well designed, quality constructed house that is a joy to live in A house that our customers are proud to call Home.</SubDescription><SubImage SequencePosition="1" Title="House1" ReferenceType="URL">http://www.chrisgeorgenewhomes.com/images/photos/about-us/101_Daigle-On-Front-Porch.jpg</SubImage><SubImage SequencePosition="2" Title="House1" ReferenceType="URL">http://www.chrisgeorgenewhomes.com/lib/image.asp?ImageID=267542&amp;ImageType=0</SubImage><SubImage SequencePosition="3" Title="House1" ReferenceType="URL">http://www.chrisgeorgenewhomes.com/lib/image.asp?ImageID=267401&amp;ImageType=0</SubImage><SubWebsite>http://www.chrisgeorgenewhomes.com/</SubWebsite><Plan Type="SingleFamily"><PlanNumber>916778468687929192020221387502</PlanNumber><PlanName>The Niantic</PlanName><PlanNotAvailable>0</PlanNotAvailable><PlanTypeName>Single Family</PlanTypeName><BasePrice>0.00</BasePrice><BaseSqft>0</BaseSqft><Baths>2</Baths><HalfBaths>1</HalfBaths><Bedrooms MasterBedLocation="Down">4</Bedrooms><Garage>0.0</Garage><Description>Step in from the optional front porch to this open plan with plenty of "gathering space" for friends and family. The dramatic living room with vaulted ceiling opens to a spacious and bright island kitchen and dining room. A first floor master suite can be your own special retreat.  Three additional bedrooms, a spacious bath and hall overlooking the living room below, complete the second floor of this charming cottage.</Description><PlanImages><ElevationImage SequencePosition="1" ReferenceType="URL">http://www.chrisgeorgenewhomes.com/lib/image.asp?ImageID=254285&amp;ImageType=0</ElevationImage><ElevationImage SequencePosition="2" ReferenceType="URL">http://www.chrisgeorgenewhomes.com/lib/image.asp?ImageID=254298&amp;ImageType=0</ElevationImage><ElevationImage SequencePosition="3" ReferenceType="URL">http://www.chrisgeorgenewhomes.com/lib/image.asp?ImageID=254299&amp;ImageType=0</ElevationImage></PlanImages><PlanWebsite>http://www.chrisgeorgenewhomes.com/docs/inventory/plan-details.asp?planID=55115</PlanWebsite></Plan></Subdivision></Builder></Corporation></Builders>